ovos_microphone_plugin_alsa/__init__.py
ovos_microphone_plugin_alsa/version.py
ovos_microphone_plugin_alsa-0.1.3.dist-info/licenses/LICENSE
ovos_microphone_plugin_alsa-0.1.3.dist-info/METADATA
ovos_microphone_plugin_alsa-0.1.3.dist-info/WHEEL
ovos_microphone_plugin_alsa-0.1.3.dist-info/entry_points.txt
ovos_microphone_plugin_alsa-0.1.3.dist-info/top_level.txt
ovos_microphone_plugin_alsa-0.1.3.dist-info/zip-safe
ovos_microphone_plugin_alsa-0.1.3.dist-info/RECORD
